pygogo/__init__.py
pygogo/formatters.py
pygogo/handlers.py
pygogo/main.py
pygogo/utils.py
pygogo-1.3.0.data/scripts/gogo
pygogo-1.3.0.dist-info/METADATA
pygogo-1.3.0.dist-info/RECORD
pygogo-1.3.0.dist-info/WHEEL
pygogo-1.3.0.dist-info/top_level.txt
