Metadata-Version: 2.1
Name: pygogo
Version: 1.3.0
Summary: A Python logging library with super powers
Home-page: https://github.com/reubano/pygogo
Author: Reuben Cummings
Author-email: reubano@gmail.com
License: MIT
Download-URL: https://github.com/reubano/pygogo/archive/v1.3.0.tar.gz
Keywords: pygogo,A,Python,logging,library,with,super,powers
Platform: MacOS X
Platform: Windows
Platform: Linux
Classifier: License :: OSI Approved :: MIT License
Classifier: Development Status :: 5 - Production/Stable
Classifier: Natural Language :: English
Classifier: Programming Language :: Python :: 3
Classifier: Programming Language :: Python :: 3 :: Only
Classifier: Programming Language :: Python :: 3.7
Classifier: Programming Language :: Python :: 3.8
Classifier: Programming Language :: Python :: 3.9
Classifier: Programming Language :: Python :: Implementation :: CPython
Classifier: Programming Language :: Python :: Implementation :: PyPy
Classifier: Environment :: Console
Classifier: Topic :: Software Development :: Libraries :: Python Modules
Classifier: Intended Audience :: Developers
Classifier: Operating System :: POSIX :: Linux
Classifier: Operating System :: MacOS :: MacOS X
Classifier: Operating System :: Microsoft :: Windows
Provides-Extra: develop
Provides-Extra: develop
Requires-Dist: pip (>20.0); extra == 'develop'
Requires-Dist: wheel (>=0.29.0); extra == 'develop'
Requires-Dist: black (<22.0,>=19.3b0); extra == 'develop'
Requires-Dist: coverage (<7.0.0,>=4.0.0); extra == 'develop'
Requires-Dist: flake8 (<5.0.0,>=3.7.9); extra == 'develop'
Requires-Dist: flake8-black (<0.3.0,>=0.1.1); extra == 'develop'
Requires-Dist: manage.py (<0.3.0,>=0.2.10); extra == 'develop'
Requires-Dist: nose (<2.0.0,>=1.3.7); extra == 'develop'
Requires-Dist: pkutils (<4.0.0,>=3.0.0); extra == 'develop'
Requires-Dist: pylint (<3.0.0,>=2.5.0); extra == 'develop'
Requires-Dist: setuptools (>=42.0.2); extra == 'develop'
Requires-Dist: scripttest (<2.0,>=1.3); extra == 'develop'
Requires-Dist: tox (<4.0.0,>=3.14.3); extra == 'develop'
Requires-Dist: twine (<4.0.0,>=3.2.0); extra == 'develop'
